{
  "0": {
    "basicblocks": 860,
    "calls": "8 11 3 6 1 7 5",
    "file": "myproject.cpp",
    "fileloc": 7,
    "instructions": 2257,
    "loads": {
      "L": 98,
      "T": 84
    },
    "name": "myproject",
    "stores": {
      "L": 181,
      "T": 5
    },
    "total_instructions": 367463
  },
  "1": {
    "basicblocks": 18509,
    "calls": "2 2 2 2 2 2 2 2 2 2 2 2 2 2 2 2 2 2 2 2 2 2 2 2 2 2 2 2 2 2 2 2",
    "file": "nnet_dense_latency.h",
    "fileloc": 13,
    "instructions": 51723,
    "loads": {
      "L": 6240
    },
    "name": "dense_latency<ap_ufixed<13, 12, AP_TRN, AP_WRAP, 0>, ap_fixed<17, 15, AP_TRN, AP_WRAP, 0>, config13>",
    "stores": {
      "L": 3136
    },
    "total_instructions": 52139
  },
  "10": {
    "basicblocks": 5,
    "calls": "",
    "file": "nnet_mult.h",
    "fileloc": 110,
    "instructions": 13,
    "name": "cast<ap_fixed<15, 13, AP_TRN, AP_WRAP, 0>, ap_fixed<16, 14, AP_TRN, AP_WRAP, 0>, config3>",
    "stores": {
      "L": 3
    },
    "total_instructions": 13
  },
  "11": {
    "basicblocks": 708,
    "calls": "",
    "file": "nnet_activation.h",
    "fileloc": 39,
    "instructions": 1409,
    "loads": {
      "L": 64
    },
    "name": "relu<ap_fixed<16, 14, AP_TRN, AP_WRAP, 0>, ap_ufixed<12, 12, AP_TRN, AP_WRAP, 0>, ReLU_config6>",
    "stores": {
      "L": 128
    },
    "total_instructions": 1409
  },
  "2": {
    "basicblocks": 5,
    "calls": "",
    "file": "nnet_mult.h",
    "fileloc": 110,
    "instructions": 13,
    "name": "cast<ap_ufixed<13, 12, AP_TRN, AP_WRAP, 0>, ap_fixed<17, 15, AP_TRN, AP_WRAP, 0>, config13>",
    "stores": {
      "L": 3
    },
    "total_instructions": 13
  },
  "3": {
    "basicblocks": 45197,
    "calls": "4 4 4 4 4 4 4 4 4 4 4 4 4 4 4 4 4 4 4 4 4 4 4 4 4 4 4 4 4 4 4 4",
    "file": "nnet_dense_latency.h",
    "fileloc": 13,
    "instructions": 113550,
    "loads": {
      "L": 12416
    },
    "name": "dense_latency<ap_ufixed<12, 12, AP_TRN, AP_WRAP, 0>, ap_fixed<15, 14, AP_TRN, AP_WRAP, 0>, config8>",
    "stores": {
      "L": 6208
    },
    "total_instructions": 113966
  },
  "4": {
    "basicblocks": 5,
    "calls": "",
    "file": "nnet_mult.h",
    "fileloc": 110,
    "instructions": 13,
    "name": "cast<ap_ufixed<12, 12, AP_TRN, AP_WRAP, 0>, ap_fixed<15, 14, AP_TRN, AP_WRAP, 0>, config8>",
    "stores": {
      "L": 3
    },
    "total_instructions": 13
  },
  "5": {
    "basicblocks": 3597,
    "calls": "9 9 9 9 9",
    "file": "nnet_dense_latency.h",
    "fileloc": 13,
    "instructions": 9443,
    "loads": {
      "L": 1002
    },
    "name": "dense_latency<ap_ufixed<13, 11, AP_TRN, AP_WRAP, 0>, ap_fixed<14, 10, AP_TRN, AP_WRAP, 0>, config18>",
    "stores": {
      "L": 490
    },
    "total_instructions": 9508
  },
  "6": {
    "basicblocks": 356,
    "calls": "",
    "file": "nnet_activation.h",
    "fileloc": 39,
    "instructions": 673,
    "loads": {
      "L": 32
    },
    "name": "relu<ap_fixed<15, 14, AP_TRN, AP_WRAP, 0>, ap_ufixed<13, 12, AP_TRN, AP_WRAP, 0>, ReLU_config11>",
    "stores": {
      "L": 64
    },
    "total_instructions": 673
  },
  "7": {
    "basicblocks": 356,
    "calls": "",
    "file": "nnet_activation.h",
    "fileloc": 39,
    "instructions": 673,
    "loads": {
      "L": 32
    },
    "name": "relu<ap_fixed<17, 15, AP_TRN, AP_WRAP, 0>, ap_ufixed<13, 11, AP_TRN, AP_WRAP, 0>, ReLU_config16>",
    "stores": {
      "L": 64
    },
    "total_instructions": 673
  },
  "8": {
    "basicblocks": 74743,
    "calls": "10 10 10 10 10 10 10 10 10 10 10 10 10 10 10 10 10 10 10 10 10 10 10 10 10 10 10 10 10 10 10 10 10 10 10 10 10 10 10 10 10 10 10 10 10 10 10 10 10 10 10 10 10 10 10 10 10 10 10 10 10 10 10 10",
    "file": "nnet_dense_latency.h",
    "fileloc": 13,
    "instructions": 186006,
    "loads": {
      "L": 20533
    },
    "name": "dense_latency<ap_fixed<15, 13, AP_TRN, AP_WRAP, 0>, ap_fixed<16, 14, AP_TRN, AP_WRAP, 0>, config3>",
    "stores": {
      "L": 10304
    },
    "total_instructions": 186838
  },
  "9": {
    "basicblocks": 5,
    "calls": "",
    "file": "nnet_mult.h",
    "fileloc": 110,
    "instructions": 13,
    "name": "cast<ap_ufixed<13, 11, AP_TRN, AP_WRAP, 0>, ap_fixed<14, 10, AP_TRN, AP_WRAP, 0>, config18>",
    "stores": {
      "L": 3
    },
    "total_instructions": 13
  }
}